data_integrity/__init__.py
data_integrity/py.typed
data_integrity-0.1.0.dist-info/METADATA
data_integrity-0.1.0.dist-info/WHEEL
data_integrity-0.1.0.dist-info/RECORD
