Metadata-Version: 2.4
Name: data-integrity
Version: 0.1.0
Summary: Python library to handle W3C VC Data Integrity algorithms.
Author-email: PatStLouis <patrick.st-louis@opsecid.ca>
Requires-Python: >=3.12
